sturgmap/__init__.py
sturgmap/common.py
sturgmap/foliumap.py
sturgmap/sturgmap.py
sturgmap-0.0.6.dist-info/LICENSE
sturgmap-0.0.6.dist-info/METADATA
sturgmap-0.0.6.dist-info/WHEEL
sturgmap-0.0.6.dist-info/entry_points.txt
sturgmap-0.0.6.dist-info/top_level.txt
sturgmap-0.0.6.dist-info/RECORD
