Metadata-Version: 2.1
Name: sturgmap
Version: 0.0.6
Summary: Python package for geospatial analysis
Author-email: Nathan Sturgill <nsturgi1@vols.utk.edu>
License: MIT License
Project-URL: Homepage, https://github.com/nathansturgill/sturgmap
Keywords: sturgmap
Classifier: Intended Audience :: Developers
Classifier: License :: OSI Approved :: MIT License
Classifier: Natural Language :: English
Classifier: Programming Language :: Python :: 3.8
Classifier: Programming Language :: Python :: 3.9
Classifier: Programming Language :: Python :: 3.10
Classifier: Programming Language :: Python :: 3.11
Classifier: Programming Language :: Python :: 3.12
Requires-Python: >=3.8
License-File: LICENSE
Requires-Dist: numpy
Requires-Dist: ipyleaflet
Requires-Dist: folium
Requires-Dist: pandas
Requires-Dist: localtileserver
Provides-Extra: all
Requires-Dist: sturgmap[extra] ; extra == 'all'
Provides-Extra: extra
Requires-Dist: pandas ; extra == 'extra'
